nachshon/__init__.py
nachshon/__main__.py
nachshon/cli.py
nachshon/lexer.py
nachshon/loader.py
nachshon/parser.py
nachshon/transpiler.py
nachshon-1.0.0.dist-info/licenses/LICENSE
nachshon-1.0.0.dist-info/METADATA
nachshon-1.0.0.dist-info/WHEEL
nachshon-1.0.0.dist-info/entry_points.txt
nachshon-1.0.0.dist-info/top_level.txt
nachshon-1.0.0.dist-info/RECORD
