Metadata-Version: 2.4
Name: nachshon
Version: 1.0.0
Summary: נחשון - שפת תכנות עברית מבוססת פייתון
Author: Nachshon Team
License: MIT
Project-URL: Homepage, https://github.com/nachshon-lang/nachshon
Project-URL: Documentation, https://github.com/nachshon-lang/nachshon#readme
Project-URL: Issues, https://github.com/nachshon-lang/nachshon/issues
Keywords: hebrew,programming-language,transpiler,education,עברית
Classifier: Development Status :: 4 - Beta
Classifier: Intended Audience :: Education
Classifier: License :: OSI Approved :: MIT License
Classifier: Natural Language :: Hebrew
Classifier: Programming Language :: Python :: 3
Classifier: Programming Language :: Python :: 3.8
Classifier: Programming Language :: Python :: 3.9
Classifier: Programming Language :: Python :: 3.10
Classifier: Programming Language :: Python :: 3.11
Classifier: Programming Language :: Python :: 3.12
Classifier: Topic :: Education
Classifier: Topic :: Software Development :: Compilers
Classifier: Topic :: Software Development :: Interpreters
Requires-Python: >=3.8
License-File: LICENSE
Dynamic: license-file
